<?xml version='1.0' encoding='UTF-8'?>
<types:mule xmlns:types="http://www.mulesoft.org/schema/mule/types">
  <types:catalog>
    <types:type name="auto_aeecacd7-8e17-485d-88cc-3f3d624522ef_Input-Attributes" format="java">
      <types:shape format="weave" example="weave/autogenerated/aeecacd7-8e17-485d-88cc-3f3d624522ef/Input-Attributes.wev" autogeneratedOrigin="bb423592-e107-4d80-871e-a7b2b2118916"><![CDATA[%dw 2.0

type auto_aeecacd7_8e17_485d_88cc_3f3d624522ef_Input_Attributes = {|
  listenerPath: String, 
  rawRequestPath: String, 
  relativePath: String, 
  maskedRequestPath: String, 
  version: String, 
  scheme: String, 
  method: String, 
  requestUri: String, 
  rawRequestUri: String, 
  queryString: String, 
  localAddress: String, 
  remoteAddress: String, 
  clientCertificate?: java_security_cert_Certificate {"typeId": "java.security.cert.Certificate",
  "typeAlias": "Certificate"}, 
  queryParams: { _?: String }, 
  uriParams: { _?: String }, 
  requestPath: String, 
  headers: { _?: String }
|} {"typeId": "org.mule.extension.http.api.HttpRequestAttributes",
"typeAlias": "HttpRequestAttributes"}
type java_security_cert_Certificate = {|
  encoded?: Binary, 
  publicKey?: java_security_PublicKey {"typeId": "java.security.PublicKey",
  "typeAlias": "PublicKey"}, 
  "type"?: String
|} {"typeId": "java.security.cert.Certificate",
"typeAlias": "Certificate"}
type java_security_PublicKey = {|  |} {"typeId": "java.security.PublicKey",
"typeAlias": "PublicKey"}





]]></types:shape>
    </types:type>
    <types:type name="auto_aeecacd7-8e17-485d-88cc-3f3d624522ef_Input-Payload" format="json">
      <types:shape format="weave" example="weave/autogenerated/aeecacd7-8e17-485d-88cc-3f3d624522ef/Input-Payload.wev" autogeneratedOrigin="bb423592-e107-4d80-871e-a7b2b2118916"><![CDATA[%dw 2.0

type auto_aeecacd7_8e17_485d_88cc_3f3d624522ef_Input_Payload = {| message: String |}

]]></types:shape>
    </types:type>
    <types:type name="auto_aeecacd7-8e17-485d-88cc-3f3d624522ef_Output-Payload" format="json">
      <types:shape format="weave" example="weave/autogenerated/aeecacd7-8e17-485d-88cc-3f3d624522ef/Output-Payload.wev" autogeneratedOrigin="bb423592-e107-4d80-871e-a7b2b2118916"><![CDATA[%dw 2.0

type auto_aeecacd7_8e17_485d_88cc_3f3d624522ef_Output_Payload = {| message: String |}

]]></types:shape>
    </types:type>
    <types:type name="auto_aeecacd7-8e17-485d-88cc-3f3d624522ef_Output-Attributes" format="java">
      <types:shape format="weave" example="weave/autogenerated/aeecacd7-8e17-485d-88cc-3f3d624522ef/Output-Attributes.wev" autogeneratedOrigin="bb423592-e107-4d80-871e-a7b2b2118916"><![CDATA[%dw 2.0

type auto_aeecacd7_8e17_485d_88cc_3f3d624522ef_Output_Attributes = {|
  listenerPath: String, 
  rawRequestPath: String, 
  relativePath: String, 
  maskedRequestPath: String, 
  version: String, 
  scheme: String, 
  method: String, 
  requestUri: String, 
  rawRequestUri: String, 
  queryString: String, 
  localAddress: String, 
  remoteAddress: String, 
  clientCertificate?: java_security_cert_Certificate {"typeId": "java.security.cert.Certificate",
  "typeAlias": "Certificate"}, 
  queryParams: { _?: String }, 
  uriParams: { _?: String }, 
  requestPath: String, 
  headers: { _?: String }
|} {"typeId": "org.mule.extension.http.api.HttpRequestAttributes",
"typeAlias": "HttpRequestAttributes"}
type java_security_cert_Certificate = {|
  encoded?: Binary, 
  publicKey?: java_security_PublicKey {"typeId": "java.security.PublicKey",
  "typeAlias": "PublicKey"}, 
  "type"?: String
|} {"typeId": "java.security.cert.Certificate",
"typeAlias": "Certificate"}
type java_security_PublicKey = {|  |} {"typeId": "java.security.PublicKey",
"typeAlias": "PublicKey"}





]]></types:shape>
    </types:type>
  </types:catalog>
  <types:enrichment select="#aeecacd7-8e17-485d-88cc-3f3d624522ef">
    <types:processor-declaration>
      <types:input-event>
        <types:message>
          <types:payload type="auto_aeecacd7-8e17-485d-88cc-3f3d624522ef_Input-Payload"/>
          <types:attributes type="auto_aeecacd7-8e17-485d-88cc-3f3d624522ef_Input-Attributes"/>
        </types:message>
      </types:input-event>
      <types:output-event>
        <types:message>
          <types:payload type="auto_aeecacd7-8e17-485d-88cc-3f3d624522ef_Output-Payload"/>
          <types:attributes type="auto_aeecacd7-8e17-485d-88cc-3f3d624522ef_Output-Attributes"/>
        </types:message>
      </types:output-event>
    </types:processor-declaration>
  </types:enrichment>
</types:mule>